gio_tracker/__init__.py
gio_tracker/async_buffered_consumer.py
gio_tracker/buffered_consumer.py
gio_tracker/consumer.py
gio_tracker/data_parser.py
gio_tracker/debug_consumer.py
gio_tracker/default_consumer.py
gio_tracker/message.py
gio_tracker/version.py
gio_tracker_snappy/__init__.py
gio_tracker_snappy/snappy_parser.py
gio_tracker-0.1.0.dist-info/LICENSE.txt
gio_tracker-0.1.0.dist-info/METADATA
gio_tracker-0.1.0.dist-info/WHEEL
gio_tracker-0.1.0.dist-info/top_level.txt
gio_tracker-0.1.0.dist-info/RECORD
